django_project_base/__init__.py
django_project_base/apps.py
django_project_base/constants.py
django_project_base/country_holidays.py
django_project_base/models.py
django_project_base/package.json
django_project_base/router.py
django_project_base/serialization.py
django_project_base/settings.py
django_project_base/settings_parser.py
django_project_base/urls.py
django_project_base/utils.py
django_project_base/views.py
django_project_base/account/__init__.py
django_project_base/account/apps.py
django_project_base/account/authentication.py
django_project_base/account/constants.py
django_project_base/account/middleware.py
django_project_base/account/router.py
django_project_base/account/settings.py
django_project_base/account/urls.py
django_project_base/account/management/__init__.py
django_project_base/account/management/commands/__init__.py
django_project_base/account/management/commands/allauth_to_social_core.py
django_project_base/account/management/commands/delete_users.py
django_project_base/account/rest/__init__.py
django_project_base/account/rest/account.py
django_project_base/account/rest/impersonate.py
django_project_base/account/rest/invite.py
django_project_base/account/rest/login.py
django_project_base/account/rest/profile.py
django_project_base/account/rest/profile_merge.py
django_project_base/account/rest/project_profiles.py
django_project_base/account/rest/project_profiles_utils.py
django_project_base/account/rest/reset_password.py
django_project_base/account/service/__init__.py
django_project_base/account/service/merge_users_service.py
django_project_base/account/service/register_user_service.py
django_project_base/account/service/reset_password_email_service.py
django_project_base/account/social_auth/__init__.py
django_project_base/account/social_auth/providers.py
django_project_base/account/social_auth/settings.py
django_project_base/auth/__init__.py
django_project_base/auth/admin.py
django_project_base/auth/apps.py
django_project_base/auth/models.py
django_project_base-0.81.17.dist-info/METADATA
django_project_base-0.81.17.dist-info/WHEEL
django_project_base-0.81.17.dist-info/licenses/LICENSE
django_project_base-0.81.17.dist-info/RECORD
