Metadata-Version: 2.4
Name: django-project-base
Version: 0.81.17
Summary: Everything revolves around it: users, roles, permissions, tags, etc.
Project-URL: Homepage, https://github.com/velis74/django-project-base
Project-URL: Repository, https://github.com/velis74/django-project-base
Project-URL: Bug Tracker, https://github.com/velis74/django-project-base/issues
Author-email: Jure Erznožnik <support@velis.si>
License: Proprietary
License-File: LICENSE
Classifier: Development Status :: 3 - Alpha
Classifier: Framework :: Django
Classifier: License :: Other/Proprietary License
Classifier: Operating System :: OS Independent
Classifier: Programming Language :: Python :: 3
Requires-Python: >=3.8
Requires-Dist: boto3
Requires-Dist: celery>=5.2
Requires-Dist: click>=8.1
Requires-Dist: django
Requires-Dist: django-csp
Requires-Dist: django-hijack<3
Requires-Dist: django-permissions-policy
Requires-Dist: django-rest-registration
Requires-Dist: django-taggit
Requires-Dist: djangorestframework
Requires-Dist: drf-spectacular<0.26.0,>=0.17.2
Requires-Dist: dynamicforms>=0.80.17
Requires-Dist: natural
Requires-Dist: pandas
Requires-Dist: pytz
Requires-Dist: requests
Requires-Dist: social-auth-app-django
Requires-Dist: svgwrite
Requires-Dist: swapper
